django_fitbit-0.2.2.dist-info/DESCRIPTION.rst
django_fitbit-0.2.2.dist-info/METADATA
django_fitbit-0.2.2.dist-info/metadata.json
django_fitbit-0.2.2.dist-info/RECORD
django_fitbit-0.2.2.dist-info/top_level.txt
django_fitbit-0.2.2.dist-info/WHEEL
fitapp/__init__.py
fitapp/decorators.py
fitapp/defaults.py
fitapp/forms.py
fitapp/models.py
fitapp/tasks.py
fitapp/urls.py
fitapp/utils.py
fitapp/views.py
fitapp/fixtures/initial_data.json
fitapp/migrations/0001_initial.py
fitapp/migrations/0002_initial_data.py
fitapp/migrations/0003_add_refresh_token_field.py
fitapp/migrations/0004_rename_auth_token_to_access_token.py
fitapp/migrations/0005_upgrade_oauth1_tokens_to_oauth2.py
fitapp/migrations/__init__.py
fitapp/south_migrations/0001_initial.py
fitapp/south_migrations/0002_auto__add_timeseriesdatatype__add_unique_timeseriesdatatype_category_r.py
fitapp/south_migrations/0003_auto__add_unique_userfitbit_fitbit_user.py
fitapp/south_migrations/__init__.py
fitapp/templates/fitapp/error.html
fitapp/templatetags/__init__.py
fitapp/templatetags/fitbit.py
fitapp/tests/__init__.py
fitapp/tests/base.py
fitapp/tests/celery.py
fitapp/tests/test_integration.py
fitapp/tests/test_models.py
fitapp/tests/test_retrieval.py
fitapp/tests/test_utils.py
fitapp/tests/test_verification.py
